luchtmeetnet/__init__.py
luchtmeetnet/constants.py
luchtmeetnet/luchtmeetnet.py
luchtmeetnet/urls.py
luchtmeetnet-0.0.2.dist-info/LICENSE
luchtmeetnet-0.0.2.dist-info/METADATA
luchtmeetnet-0.0.2.dist-info/WHEEL
luchtmeetnet-0.0.2.dist-info/top_level.txt
luchtmeetnet-0.0.2.dist-info/RECORD
