Metadata-Version: 2.1
Name: luchtmeetnet
Version: 0.0.2
Summary: Package for luchtmeetned (Dutch)
Home-page: https://github.com/magtimmermans/python_luchtmeetnet
Author: Marcel Timmermans
Author-email: marcel@timmermans.us
License: UNKNOWN
Platform: UNKNOWN
Classifier: Programming Language :: Python :: 3
Classifier: License :: OSI Approved :: MIT License
Classifier: Operating System :: OS Independent
Requires-Python: >=3.6
